darwinexapis/__init__.py
darwinexapis/API/DWX_API_Auth.py
darwinexapis/API/__init__.py
darwinexapis/API/dwx_api.py
darwinexapis/API/DarwinDataAnalyticsAPI/DWX_Data_Analytics_API.py
darwinexapis/API/DarwinDataAnalyticsAPI/FTP_DARWIN_Access_Credentials.cfg
darwinexapis/API/DarwinDataAnalyticsAPI/README.rst
darwinexapis/API/DarwinDataAnalyticsAPI/__init__.py
darwinexapis/API/DarwinDataAnalyticsAPI/__pycache__/DWX_Data_Analytics_API.cpython-38.pyc
darwinexapis/API/DarwinDataAnalyticsAPI/__pycache__/__init__.cpython-38.pyc
darwinexapis/API/InfoAPI/DWX_Info_API.py
darwinexapis/API/InfoAPI/__init__.py
darwinexapis/API/InfoAPI/__pycache__/DWX_Info_API.cpython-38.pyc
darwinexapis/API/InfoAPI/__pycache__/__init__.cpython-38.pyc
darwinexapis/API/InvestorAccountInfoAPI/DWX_AccInfo_API.py
darwinexapis/API/InvestorAccountInfoAPI/__init__.py
darwinexapis/API/InvestorAccountInfoAPI/__pycache__/DWX_AccInfo_API.cpython-38.pyc
darwinexapis/API/InvestorAccountInfoAPI/__pycache__/__init__.cpython-38.pyc
darwinexapis/API/QuotesAPI/DWX_Quotes_API.py
darwinexapis/API/QuotesAPI/__init__.py
darwinexapis/API/QuotesAPI/__pycache__/DWX_Quotes_API.cpython-38.pyc
darwinexapis/API/QuotesAPI/__pycache__/__init__.cpython-38.pyc
darwinexapis/API/TickDataAPI/DWX_TickData_Downloader_API.py
darwinexapis/API/TickDataAPI/DWX_TickData_Reader_API.py
darwinexapis/API/TickDataAPI/__init__.py
darwinexapis/API/TickDataAPI/__pycache__/DWX_TickData_Downloader_API.cpython-38.pyc
darwinexapis/API/TickDataAPI/__pycache__/DWX_TickData_Reader_API.cpython-38.pyc
darwinexapis/API/TickDataAPI/__pycache__/__init__.cpython-38.pyc
darwinexapis/API/TradingAPI/DWX_Trading_API.py
darwinexapis/API/TradingAPI/__init__.py
darwinexapis/API/TradingAPI/__pycache__/DWX_Trading_API.cpython-38.pyc
darwinexapis/API/TradingAPI/__pycache__/__init__.cpython-38.pyc
darwinexapis/API/WebSocketAPI/DWX_WebSocket_API.py
darwinexapis/API/WebSocketAPI/__init__.py
darwinexapis/API/WebSocketAPI/__pycache__/DWX_WebSocket_API.cpython-38.pyc
darwinexapis-0.4.5.dist-info/LICENSE.txt
darwinexapis-0.4.5.dist-info/METADATA
darwinexapis-0.4.5.dist-info/WHEEL
darwinexapis-0.4.5.dist-info/top_level.txt
darwinexapis-0.4.5.dist-info/RECORD
