Metadata-Version: 2.1
Name: darwinexapis
Version: 0.4.5
Summary: Python wrapper for Darwinex APIs
Home-page: https://github.com/darwinex/darwinexapis
Author: Alpha Team @ DWX
Author-email: content@darwinex.com
License: BSD
Keywords: darwinex algorithmic trading quant quantitative analysis asyncio websockets darwins async
Platform: any
Classifier: Development Status :: 4 - Beta
Classifier: Intended Audience :: Developers
Classifier: Topic :: Office/Business :: Financial :: Investment
Classifier: License :: OSI Approved :: BSD License
Classifier: Programming Language :: Python :: 3.6
Classifier: Programming Language :: Python :: 3 :: Only
Requires-Python: >=3.6
Requires-Dist: pandas
Requires-Dist: plotly
Requires-Dist: matplotlib
Requires-Dist: requests
Requires-Dist: websockets
Requires-Dist: tqdm
Requires-Dist: dash
Requires-Dist: pyftpdlib
Requires-Dist: tables
